gsystemctl/__init__.py
gsystemctl/config.py
gsystemctl/globals.py
gsystemctl/gsystemctl.ini
gsystemctl/systemctl.py
gsystemctl/version.py
gsystemctl/ui/__init__.py
gsystemctl/ui/application.py
gsystemctl/ui/dialogs.py
gsystemctl/ui/mainwindow.py
gsystemctl/ui/menus.py
gsystemctl/ui/systemditem.py
gsystemctl/ui/systemditemfactory.py
gsystemctl/ui/systemditemfilter.py
gsystemctl/ui/systemditemnotebook.py
gsystemctl/ui/systemditemscrolled.py
gsystemctl/ui/systemditemsorter.py
gsystemctl/ui/images/gsystemctl-logo.png
gsystemctl-0.5.0.data/data/share/applications/gsystemctl.desktop
gsystemctl-0.5.0.data/data/share/icons/hicolor/128x128/apps/gsystemctl.png
gsystemctl-0.5.0.data/data/share/icons/hicolor/16x16/apps/gsystemctl.png
gsystemctl-0.5.0.data/data/share/icons/hicolor/24x24/apps/gsystemctl.png
gsystemctl-0.5.0.data/data/share/icons/hicolor/256x256/apps/gsystemctl.png
gsystemctl-0.5.0.data/data/share/icons/hicolor/32x32/apps/gsystemctl.png
gsystemctl-0.5.0.data/data/share/icons/hicolor/48x48/apps/gsystemctl.png
gsystemctl-0.5.0.dist-info/AUTHORS
gsystemctl-0.5.0.dist-info/COPYING
gsystemctl-0.5.0.dist-info/METADATA
gsystemctl-0.5.0.dist-info/WHEEL
gsystemctl-0.5.0.dist-info/entry_points.txt
gsystemctl-0.5.0.dist-info/top_level.txt
gsystemctl-0.5.0.dist-info/RECORD
