Metadata-Version: 2.1
Name: gsystemctl
Version: 0.5.0
Summary: Control the systemd service manager with Gtk GUI, instead of console
Home-page: https://github.com/ferkretz/gsystemctl
Author: Ferenc Kretz
Author-email: ferkretz@gmail.com
License: GPLv3
Classifier: Programming Language :: Python :: 3
Classifier: License :: OSI Approved :: GNU General Public License v3 (GPLv3)
Classifier: Operating System :: POSIX :: Linux
Classifier: Development Status :: 5 - Production/Stable
Classifier: Environment :: X11 Applications :: GTK
Classifier: Topic :: System :: Monitoring
Classifier: Topic :: System :: Systems Administration
Classifier: Natural Language :: English
Requires-Python: >=3.10
License-File: COPYING
License-File: AUTHORS
Requires-Dist: PyGObject>=3.40
